a_sqa_sdk-2.0.8.dist-info/licenses/LICENSE
spotifywebapiwithfixesandimprovementsfromsonallux/__init__.py
spotifywebapiwithfixesandimprovementsfromsonallux/api_helper.py
spotifywebapiwithfixesandimprovementsfromsonallux/configuration.py
spotifywebapiwithfixesandimprovementsfromsonallux/spotifywebapiwithfixesandimprovementsfromsonallux_client.py
spotifywebapiwithfixesandimprovementsfromsonallux/controllers/__init__.py
spotifywebapiwithfixesandimprovementsfromsonallux/controllers/albums_controller.py
spotifywebapiwithfixesandimprovementsfromsonallux/controllers/artists_controller.py
spotifywebapiwithfixesandimprovementsfromsonallux/controllers/audiobooks_controller.py
spotifywebapiwithfixesandimprovementsfromsonallux/controllers/base_controller.py
spotifywebapiwithfixesandimprovementsfromsonallux/controllers/categories_controller.py
spotifywebapiwithfixesandimprovementsfromsonallux/controllers/chapters_controller.py
spotifywebapiwithfixesandimprovementsfromsonallux/controllers/episodes_controller.py
spotifywebapiwithfixesandimprovementsfromsonallux/controllers/genres_controller.py
spotifywebapiwithfixesandimprovementsfromsonallux/controllers/markets_controller.py
spotifywebapiwithfixesandimprovementsfromsonallux/controllers/o_auth_authorization_controller.py
spotifywebapiwithfixesandimprovementsfromsonallux/controllers/player_controller.py
spotifywebapiwithfixesandimprovementsfromsonallux/controllers/playlists_controller.py
spotifywebapiwithfixesandimprovementsfromsonallux/controllers/search_controller.py
spotifywebapiwithfixesandimprovementsfromsonallux/controllers/shows_controller.py
spotifywebapiwithfixesandimprovementsfromsonallux/controllers/tracks_controller.py
spotifywebapiwithfixesandimprovementsfromsonallux/controllers/users_controller.py
spotifywebapiwithfixesandimprovementsfromsonallux/exceptions/__init__.py
spotifywebapiwithfixesandimprovementsfromsonallux/exceptions/api_exception.py
spotifywebapiwithfixesandimprovementsfromsonallux/exceptions/bad_request_exception.py
a_sqa_sdk-2.0.8.dist-info/METADATA
a_sqa_sdk-2.0.8.dist-info/WHEEL
a_sqa_sdk-2.0.8.dist-info/top_level.txt
a_sqa_sdk-2.0.8.dist-info/RECORD
